e_simulator/__init__.py
e_simulator/geometry/__init__.py
e_simulator/geometry/geometry.py
e_simulator/geometry/vector.py
e_simulator/simulation/__init__.py
e_simulator/simulation/constants.py
e_simulator/simulation/em_field.py
e_simulator/simulation/em_region.py
e_simulator/simulation/particle.py
e_simulator/simulation/project.py
e_simulator/simulation/simulator.py
e_simulator/utils/__init__.py
e_simulator/utils/color.py
e_simulator/visualization/__init__.py
e_simulator/visualization/animation.py
e_simulator/visualization/bounds_limit.py
e_simulator/visualization/plot.py
e_simulator/visualization/visualizer.py
e_simulator-0.1.1.dist-info/METADATA
e_simulator-0.1.1.dist-info/WHEEL
e_simulator-0.1.1.dist-info/RECORD
